<?xml version="1.0" encoding="UTF-8"?>



<iqss>
    <dataarea id="1" t="72" l="205" w="288" h="78" f="0" val="(CRS," />

    <dataarea id="2" t="74" l="903" w="189" h="79" f="1" val="eaiuers" />

    <dataarea id="3" t="114" l="1116" w="126" h="32" f="2" val="gwen" />

    <dataarea id="4" t="771" l="0" w="2113" h="2867" f="3" val="___" />

    <dataarea id="5" t="67" l="1440" w="109" h="49" f="4" val="Cell" />

    <dataarea id="6" t="78" l="1573" w="12" h="35" f="5" val=":" />

    <dataarea id="7" t="70" l="1608" w="172" h="48" f="6" val="74015" />

    <dataarea id="8" t="72" l="1800" w="171" h="49" f="4" val="04748" />

    <dataarea id="9" t="157" l="205" w="288" h="76" f="7" val="[Mark]" />

    <dataarea id="10" t="185" l="531" w="19" h="23" f="8" val="," />

    <dataarea id="11" t="771" l="0" w="2113" h="2867" f="3" val="-" />

    <dataarea id="12" t="151" l="819" w="190" h="42" f="9" val="«k" />

    <dataarea id="13" t="257" l="471" w="109" h="40" f="10" val="*" />

    <dataarea id="14" t="771" l="0" w="2113" h="2867" f="3" val="_" />

    <dataarea id="15" t="270" l="676" w="280" h="101" f="11" val="CR." />

    <dataarea id="16" t="402" l="708" w="355" h="73" f="12" val="eurepipuuip" />

    <dataarea id="17" t="406" l="1107" w="334" h="65" f="13" val="eAMwrumtib" />

    <dataarea id="18" t="507" l="574" w="228" h="76" f="7" val="T/FE-33," />

    <dataarea id="19" t="577" l="600" w="381" h="65" f="13" val=" &#34;ComuiDGu®," />

    <dataarea id="20" t="582" l="1026" w="286" h="50" f="14" val="A#sitepent" />

    <dataarea id="21" t="602" l="1354" w="27" h="7" f="15" val="-" />

    <dataarea id="22" t="591" l="1425" w="102" h="43" f="16" val="92." />

    <dataarea id="23" t="2869" l="232" w="18" h="14" f="17" val="3" />

    <dataarea id="24" t="2864" l="363" w="43" h="14" f="17" val="mo" />





</iqss>
